{
  "variant": "az_full",
  "dataset": "cifar10",
  "epochs": 1,
  "batch_size": 32,
  "num_parameters": 262827,
  "best_val_accuracy": 43.92,
  "test_loss": 1.512488465499878,
  "test_accuracy": 45.22,
  "seconds_per_train_epoch_mean": 45.103274000342935,
  "seconds_per_forward_batch": 0.006574650062248111,
  "regularization_weights": {
    "membership_entropy": 0.0005,
    "membership_smoothness": 0.0005,
    "geometry_smoothness": 0.0005,
    "hyperbolicity_penalty": 0.001
  },
  "final_anisotropy_gap": 1.3986429072062174
}